jsontofu/__init__.py
jsontofu-1.0.0.dist-info/WHEEL
jsontofu-1.0.0.dist-info/METADATA
jsontofu-1.0.0.dist-info/RECORD
