Metadata-Version: 2.1
Name: jsontofu
Version: 1.0.0
Summary: Json raw data to object
Home-page: https://github.com/rondou/jsontofu
Author: Rondou Chen
Author-email: 40and44sis@gmail.com
Requires-Python: >=3.6.7,<4.0.0
Classifier: Programming Language :: Python :: 3
Classifier: Programming Language :: Python :: 3.7
Classifier: Programming Language :: Python :: 3.8
Requires-Dist: jsonpickle
